polytester/__init__.py
polytester/main.py
polytester/runner.py
polytester/util.py
polytester/parsers/__init__.py
polytester/parsers/base.py
polytester/parsers/default.py
polytester/parsers/django.py
polytester/parsers/karma.py
polytester/parsers/nose.py
polytester/parsers/protractor.py
polytester/parsers/pytest.py
polytester/parsers/rspec.py
polytester/parsers/salad.py
polytester/parsers/unittest.py
tests/__init__.py
tests/test_runner.py
tests/parsers/__init__.py
tests/parsers/test_nose_parser.py
tests/parsers/test_pytest_parser.py
tests/parsers/test_rspec_parser.py
polytester-1.2.3.dist-info/AUTHORS
polytester-1.2.3.dist-info/LICENSE
polytester-1.2.3.dist-info/METADATA
polytester-1.2.3.dist-info/WHEEL
polytester-1.2.3.dist-info/entry_points.txt
polytester-1.2.3.dist-info/top_level.txt
polytester-1.2.3.dist-info/RECORD
