Metadata-Version: 2.1
Name: polytester
Version: 1.2.3
Summary: A simple, easy-to-use multi-language test runner.
Home-page: https://github.com/skoczen/polytester
Download-URL: https://github.com/skoczen/polytester/archive/refs/tags/1.2.3.tar.gz
Author: Steven Skoczen
Author-email: skoczen@gmail.com
License: UNKNOWN
Keywords: test,multi-language,nose,karma,jasmine,rails,runner,junit,pytest
Platform: UNKNOWN
Classifier: Programming Language :: Python
Classifier: Intended Audience :: Developers
Classifier: License :: OSI Approved :: MIT License
Classifier: Operating System :: OS Independent
Classifier: Development Status :: 4 - Beta
Classifier: Environment :: Web Environment
Classifier: Intended Audience :: Developers
Classifier: Topic :: Software Development :: Testing
Classifier: Topic :: Software Development :: Libraries :: Python Modules
License-File: LICENSE
License-File: AUTHORS
Requires-Dist: clint
Requires-Dist: PyYAML
Requires-Dist: watchdog
